[
  {
    "toolName": "C",
    "src": "/assets/images/clang-logo.png"
  },
  {
    "toolName": "C++",
    "src": "/assets/images/cpp.png"
  },
  {
    "toolName": "NASM",
    "src": "/assets/images/nasm.png"
  },
  {
    "toolName": "Java",
    "src": "/assets/images/java.png"
  },
  {
    "toolName": "Kotlin",
    "src": "/assets/images/kotlin.png"
  },
  {
    "toolName": "Golang",
    "src": "/assets/images/golang.png"
  },
  {
    "toolName": "Python",
    "src": "/assets/images/python.png"
  },
  {
    "toolName": "Nodejs",
    "src": "/assets/images/nodejs.png"
  },
  {
    "toolName": "HTML",
    "src": "/assets/images/html-5.png"
  },
  {
    "toolName": "CSS",
    "src": "/assets/images/css3.png"
  },
  {
    "toolName": "JavaScript",
    "src": "/assets/images/javascript.png"
  },
  {
    "toolName": "TypeScript",
    "src": "/assets/images/typescript.png"
  },
  {
    "toolName": "MySQL",
    "src": "/assets/images/mysql.png"
  },
  {
    "toolName": "Bootstrap",
    "src": "/assets/images/bootstrap.png"
  },
  {
    "toolName": "JQuery",
    "src": "/assets/images/jquery.png"
  },
  {
    "toolName": "JQuery UI",
    "src": "/assets/images/jquery-ui.png"
  },
  {
    "toolName": "Swing",
    "src": "/assets/images/java.png"
  },
  {
    "toolName": "Javafx",
    "src": "/assets/images/JavaFX.png"
  },
  {
    "toolName": "React",
    "src": "/assets/images/react.svg"
  },
  {
    "toolName": "Redux",
    "src": "/assets/images/redux.png"
  },
  {
    "toolName": "React Router",
    "src": "/assets/images/react-router.png"
  },
  {
    "toolName": "Flask",
    "src": "/assets/images/flask.png"
  },
  {
    "toolName": "Expressjs",
    "src": "/assets/images/express.png"
  },
  {
    "toolName": "Git",
    "src": "/assets/images/git.png"
  },
  {
    "toolName": "Github",
    "src": "/assets/images/github.png"
  },
  {
    "toolName": "VScode",
    "src": "/assets/images/vscode.png"
  },
  {
    "toolName": "Docker",
    "src": "/assets/images/docker.png"
  },
  {
    "toolName": "Linux",
    "src": "/assets/images/linux.png"
  },
  {
    "toolName": "TimescaleDB",
    "src": "/assets/images/timescaleDB.svg"
  },
  {
    "toolName": "PostgreSQL",
    "src": "/assets/images/postgreesql.png"
  }
]
